healthcheck/__init__.py
healthcheck/filter.py
healthcheck/middleware.py
django_openstax_healthcheck-1.0.dist-info/LICENSE
django_openstax_healthcheck-1.0.dist-info/METADATA
django_openstax_healthcheck-1.0.dist-info/WHEEL
django_openstax_healthcheck-1.0.dist-info/top_level.txt
django_openstax_healthcheck-1.0.dist-info/RECORD
